aih_dynamodb/__init__.py
aih_dynamodb/database.py
aih_dynamodb/table.py
aih_dynamodb-0.5.dist-info/METADATA
aih_dynamodb-0.5.dist-info/WHEEL
aih_dynamodb-0.5.dist-info/top_level.txt
aih_dynamodb-0.5.dist-info/RECORD
